lightswitch_sdk_py/__init__.py
lightswitch_sdk_py/client.py
lightswitch_sdk_py/core.py
lightswitch_sdk_py/fastapi.py
lightswitch_sdk_py-0.2.2.dist-info/LICENSE
lightswitch_sdk_py-0.2.2.dist-info/METADATA
lightswitch_sdk_py-0.2.2.dist-info/WHEEL
lightswitch_sdk_py-0.2.2.dist-info/top_level.txt
lightswitch_sdk_py-0.2.2.dist-info/RECORD
