Metadata-Version: 2.1
Name: lightswitch-sdk-py
Version: 0.2.2
Summary: SDK for interacting with the Lightswitch backend
Author: Lightswitch Team
Author-email: team@lightswitch.com
Project-URL: Documentation, https://github.com/lightswitch/lightswitch-sdk-py
Project-URL: Source, https://github.com/lightswitch/lightswitch-sdk-py
Project-URL: Tracker, https://github.com/lightswitch/lightswitch-sdk-py/issues
Keywords: lightswitch sdk api authentication authorization
Classifier: Development Status :: 4 - Beta
Classifier: Intended Audience :: Developers
Classifier: License :: OSI Approved :: MIT License
Classifier: Programming Language :: Python :: 3
Classifier: Programming Language :: Python :: 3.7
Classifier: Programming Language :: Python :: 3.8
Classifier: Programming Language :: Python :: 3.9
Classifier: Programming Language :: Python :: 3.10
Classifier: Programming Language :: Python :: 3.11
Classifier: Programming Language :: Python :: 3.12
Requires-Python: >=3.7
License-File: LICENSE
Requires-Dist: requests >=2.25.0
Requires-Dist: python-dotenv >=0.19.0
Provides-Extra: dev
Requires-Dist: pytest >=6.0.0 ; extra == 'dev'
Requires-Dist: pytest-cov >=2.0.0 ; extra == 'dev'
Requires-Dist: black >=21.0.0 ; extra == 'dev'
Requires-Dist: flake8 >=3.8.0 ; extra == 'dev'
Provides-Extra: fastapi
Requires-Dist: fastapi >=0.68.0 ; extra == 'fastapi'
